paseto/__init__.py
paseto/crypto/.gitignore
paseto/crypto/__init__.py
paseto/crypto/libsodium.pyx
paseto/crypto/libsodium_wrapper.py
paseto/crypto/primitives.py
paseto/exceptions.py
paseto/paserk/__init__.py
paseto/paserk/keys.py
paseto/protocol/__init__.py
paseto/protocol/common.py
paseto/protocol/util.py
paseto/protocol/version2.py
paseto/protocol/version4.py
python_paseto-0.5.2.dist-info/LICENSE
python_paseto-0.5.2.dist-info/WHEEL
python_paseto-0.5.2.dist-info/METADATA
python_paseto-0.5.2.dist-info/RECORD
