Metadata-Version: 2.1
Name: python-paseto
Version: 0.5.2
Summary: Platform-Agnostic Security Tokens for Python
Home-page: https://github.com/purificant/python-paseto
License: MIT
Keywords: paseto,token,security,crypto
Requires-Python: >=3.6,<4.0
Classifier: Development Status :: 5 - Production/Stable
Classifier: License :: OSI Approved :: MIT License
Classifier: Operating System :: OS Independent
Classifier: Programming Language :: Python :: 3
Classifier: Programming Language :: Python :: 3.10
Classifier: Programming Language :: Python :: 3.6
Classifier: Programming Language :: Python :: 3.7
Classifier: Programming Language :: Python :: 3.8
Classifier: Programming Language :: Python :: 3.9
Classifier: Topic :: Security
Classifier: Topic :: Security :: Cryptography
Requires-Dist: pysodium (>=0.7.10,<0.8.0)
Project-URL: Documentation, https://github.com/purificant/python-paseto
Project-URL: Repository, https://github.com/purificant/python-paseto
